Metadata-Version: 2.1
Name: snapmlweb
Version: 0.0.1
Summary: ML Helper Webapp
Home-page: https://github.com/Parth162/snapmlweb
Author: Anish Adnani, Parth Goel
Author-email: anishadnani00@gmail.com
License: MIT
Keywords: python,coding,ml,algorithms
Platform: UNKNOWN
Classifier: Development Status :: 5 - Production/Stable
Classifier: Intended Audience :: Developers
Classifier: Programming Language :: Python :: 3
Classifier: Operating System :: Unix
Classifier: Operating System :: MacOS :: MacOS X
Classifier: Operating System :: Microsoft :: Windows
License-File: LICENCE.txt
